{
    "name": "Global Information",
    "numberOfRequests": {
        "total": 28975,
        "ok": 28975,
        "ko": 0
    },
    "minResponseTime": {
        "total": 72,
        "ok": 72,
        "ko": 0
    },
    "maxResponseTime": {
        "total": 3172,
        "ok": 3172,
        "ko": 0
    },
    "meanResponseTime": {
        "total": 84,
        "ok": 84,
        "ko": 0
    },
    "standardDeviation": {
        "total": 82,
        "ok": 82,
        "ko": 0
    },
    "percentiles1": {
        "total": 74,
        "ok": 74,
        "ko": 0
    },
    "percentiles2": {
        "total": 77,
        "ok": 77,
        "ko": 0
    },
    "percentiles3": {
        "total": 86,
        "ok": 86,
        "ko": 0
    },
    "percentiles4": {
        "total": 399,
        "ok": 399,
        "ko": 0
    },
    "group1": {
    "name": "t < 800 ms",
    "count": 28832,
    "percentage": 100
},
    "group2": {
    "name": "800 ms < t < 1200 ms",
    "count": 126,
    "percentage": 0
},
    "group3": {
    "name": "t > 1200 ms",
    "count": 17,
    "percentage": 0
},
    "group4": {
    "name": "failed",
    "count": 0,
    "percentage": 0
},
    "meanNumberOfRequestsPerSecond": {
        "total": 22.996031746031747,
        "ok": 22.996031746031747,
        "ko": 0
    }
}